[
  {
    "id": 5522,
    "name": "遠雄",
    "DividendRecentAvg": 0.15518,
    "DividendRecentSlope": -0.00672,
    "Category": "營建",
    "CurrentClosingPrice": 62.2,
    "CurrentTrend": 2.1,
    "CurrentTrendPercent": 0.0349,
    "CurrentTurnover": 8616,
    "CurrentPE": 13.07,
    "CurrentPEAvg": 38.03,
    "CurrentRecentTrendPercent": 0.0596,
    "CurrentRecentTrendComment": "連3漲",
    "URL": "https://tw.stock.yahoo.com/quote/5522/dividend"
  },
  {
    "id": 2542,
    "name": "興富發",
    "DividendRecentAvg": 0.04534,
    "DividendRecentSlope": null,
    "Category": "營建",
    "CurrentClosingPrice": 41.45,
    "CurrentTrend": -0.15,
    "CurrentTrendPercent": -0.0036,
    "CurrentTurnover": 11600,
    "CurrentPE": 31.17,
    "CurrentPEAvg": 38.03,
    "CurrentRecentTrendPercent": 0.0036,
    "CurrentRecentTrendComment": "連2漲→跌",
    "URL": "https://tw.stock.yahoo.com/quote/2542/dividend"
  },
  {
    "id": 3008,
    "name": "大立光",
    "DividendRecentAvg": 0.04084,
    "DividendRecentSlope": 0.0032,
    "Category": "光電",
    "CurrentClosingPrice": 2120,
    "CurrentTrend": -80,
    "CurrentTrendPercent": -0.0364,
    "CurrentTurnover": 842,
    "CurrentPE": 15.81,
    "CurrentPEAvg": 38.75,
    "CurrentRecentTrendPercent": 0.0364,
    "CurrentRecentTrendComment": "平→跌",
    "URL": "https://tw.stock.yahoo.com/quote/3008/dividend"
  },
  {
    "id": 2458,
    "name": "義隆",
    "DividendRecentAvg": 0.0329,
    "DividendRecentSlope": 0.00372,
    "Category": "半導體",
    "CurrentClosingPrice": 155,
    "CurrentTrend": -6.5,
    "CurrentTrendPercent": -0.0402,
    "CurrentTurnover": 3910,
    "CurrentPE": 20.58,
    "CurrentPEAvg": 69.96,
    "CurrentRecentTrendPercent": 0.0432,
    "CurrentRecentTrendComment": "連2跌",
    "URL": "https://tw.stock.yahoo.com/quote/2458/dividend"
  },
  {
    "id": 2101,
    "name": "南港",
    "DividendRecentAvg": 0.02172,
    "DividendRecentSlope": -0.0165,
    "Category": "橡膠",
    "CurrentClosingPrice": 50,
    "CurrentTrend": 2.5,
    "CurrentTrendPercent": 0.0526,
    "CurrentTurnover": 49392,
    "CurrentPE": 312.5,
    "CurrentPEAvg": 58.25,
    "CurrentRecentTrendPercent": 0.0834,
    "CurrentRecentTrendComment": "連2漲",
    "URL": "https://tw.stock.yahoo.com/quote/2101/dividend"
  },
  {
    "id": 1102,
    "name": "亞泥",
    "DividendRecentAvg": 0.02052,
    "DividendRecentSlope": null,
    "Category": "水泥",
    "CurrentClosingPrice": 42,
    "CurrentTrend": -0.15,
    "CurrentTrendPercent": -0.0036,
    "CurrentTurnover": 7753,
    "CurrentPE": 13.68,
    "CurrentPEAvg": 42.21,
    "CurrentRecentTrendPercent": 0.0036,
    "CurrentRecentTrendComment": "連2漲→跌",
    "URL": "https://tw.stock.yahoo.com/quote/1102/dividend"
  },
  {
    "id": 6271,
    "name": "同欣電",
    "DividendRecentAvg": 0.0084,
    "DividendRecentSlope": null,
    "Category": "半導體",
    "CurrentClosingPrice": 142,
    "CurrentTrend": -6.5,
    "CurrentTrendPercent": -0.0438,
    "CurrentTurnover": 4261,
    "CurrentPE": 25.96,
    "CurrentPEAvg": 69.96,
    "CurrentRecentTrendPercent": 0.0627,
    "CurrentRecentTrendComment": "連2跌",
    "URL": "https://tw.stock.yahoo.com/quote/6271/dividend"
  },
  {
    "id": 2884,
    "name": "玉山金",
    "DividendRecentAvg": 0.0064,
    "DividendRecentSlope": null,
    "Category": "金融業",
    "CurrentClosingPrice": 26.55,
    "CurrentTrend": -0.45,
    "CurrentTrendPercent": -0.0167,
    "CurrentTurnover": 39668,
    "CurrentPE": 19.1,
    "CurrentPEAvg": 14.1,
    "CurrentRecentTrendPercent": 0.0167,
    "CurrentRecentTrendComment": "連2漲→跌",
    "URL": "https://tw.stock.yahoo.com/quote/2884/dividend"
  },
  {
    "id": 2915,
    "name": "潤泰全",
    "DividendRecentAvg": 0.006,
    "DividendRecentSlope": null,
    "Category": "貿易百貨",
    "CurrentClosingPrice": 59.6,
    "CurrentTrend": -0.4,
    "CurrentTrendPercent": -0.0067,
    "CurrentTurnover": 2992,
    "CurrentPE": 8.49,
    "CurrentPEAvg": 30.95,
    "CurrentRecentTrendPercent": 0.0067,
    "CurrentRecentTrendComment": "連2漲→跌",
    "URL": "https://tw.stock.yahoo.com/quote/2915/dividend"
  },
  {
    "id": 1101,
    "name": "台泥",
    "DividendRecentAvg": 0.0044,
    "DividendRecentSlope": null,
    "Category": "水泥",
    "CurrentClosingPrice": 32,
    "CurrentTrend": -0.7,
    "CurrentTrendPercent": -0.0214,
    "CurrentTurnover": 27793,
    "CurrentPE": 31.07,
    "CurrentPEAvg": 42.21,
    "CurrentRecentTrendPercent": 0.0214,
    "CurrentRecentTrendComment": "連4漲→跌",
    "URL": "https://tw.stock.yahoo.com/quote/1101/dividend"
  },
  {
    "id": 2881,
    "name": "富邦金",
    "DividendRecentAvg": 0.004,
    "DividendRecentSlope": 0.00125,
    "Category": "金融業",
    "CurrentClosingPrice": 65,
    "CurrentTrend": -1.3,
    "CurrentTrendPercent": -0.0196,
    "CurrentTurnover": 28929,
    "CurrentPE": 14.38,
    "CurrentPEAvg": 14.1,
    "CurrentRecentTrendPercent": 0.0196,
    "CurrentRecentTrendComment": "連2漲→跌",
    "URL": "https://tw.stock.yahoo.com/quote/2881/dividend"
  },
  {
    "id": 2887,
    "name": "台新金",
    "DividendRecentAvg": 0.0034,
    "DividendRecentSlope": 0.0005,
    "Category": "金融業",
    "CurrentClosingPrice": 17.35,
    "CurrentTrend": -0.25,
    "CurrentTrendPercent": -0.0142,
    "CurrentTurnover": 35420,
    "CurrentPE": 16.06,
    "CurrentPEAvg": 14.1,
    "CurrentRecentTrendPercent": 0.0142,
    "CurrentRecentTrendComment": "連2漲→跌",
    "URL": "https://tw.stock.yahoo.com/quote/2887/dividend"
  },
  {
    "id": 2885,
    "name": "元大金",
    "DividendRecentAvg": 0.002,
    "DividendRecentSlope": null,
    "Category": "金融業",
    "CurrentClosingPrice": 29.9,
    "CurrentTrend": -0.7,
    "CurrentTrendPercent": -0.0229,
    "CurrentTurnover": 49740,
    "CurrentPE": 14.31,
    "CurrentPEAvg": 14.1,
    "CurrentRecentTrendPercent": 0.0229,
    "CurrentRecentTrendComment": "連2漲→跌",
    "URL": "https://tw.stock.yahoo.com/quote/2885/dividend"
  },
  {
    "id": 6409,
    "name": "旭隼",
    "DividendRecentAvg": 0.002,
    "DividendRecentSlope": null,
    "Category": "其他電子",
    "CurrentClosingPrice": 1515,
    "CurrentTrend": -85,
    "CurrentTrendPercent": -0.0531,
    "CurrentTurnover": 287,
    "CurrentPE": 36.69,
    "CurrentPEAvg": 24.08,
    "CurrentRecentTrendPercent": 0.0706,
    "CurrentRecentTrendComment": "連2跌",
    "URL": "https://tw.stock.yahoo.com/quote/6409/dividend"
  },
  {
    "id": 1477,
    "name": "聚陽",
    "DividendRecentAvg": 0.0014,
    "DividendRecentSlope": null,
    "Category": "紡織",
    "CurrentClosingPrice": 380.5,
    "CurrentTrend": 4.5,
    "CurrentTrendPercent": 0.012,
    "CurrentTurnover": 2570,
    "CurrentPE": 23.06,
    "CurrentPEAvg": 45.71,
    "CurrentRecentTrendPercent": 0.034,
    "CurrentRecentTrendComment": "連3漲",
    "URL": "https://tw.stock.yahoo.com/quote/1477/dividend"
  },
  {
    "id": 2886,
    "name": "兆豐金",
    "DividendRecentAvg": 0.0004,
    "DividendRecentSlope": 0,
    "Category": "金融業",
    "CurrentClosingPrice": 38.7,
    "CurrentTrend": -0.5,
    "CurrentTrendPercent": -0.0128,
    "CurrentTurnover": 44741,
    "CurrentPE": 16.4,
    "CurrentPEAvg": 14.1,
    "CurrentRecentTrendPercent": 0.0128,
    "CurrentRecentTrendComment": "漲→跌",
    "URL": "https://tw.stock.yahoo.com/quote/2886/dividend"
  },
  {
    "id": 1476,
    "name": "儒鴻",
    "DividendRecentAvg": 0,
    "DividendRecentSlope": 0,
    "Category": "紡織",
    "CurrentClosingPrice": 487,
    "CurrentTrend": -13,
    "CurrentTrendPercent": -0.026,
    "CurrentTurnover": 1303,
    "CurrentPE": 25.81,
    "CurrentPEAvg": 45.71,
    "CurrentRecentTrendPercent": 0.026,
    "CurrentRecentTrendComment": "漲→跌",
    "URL": "https://tw.stock.yahoo.com/quote/1476/dividend"
  },
  {
    "id": 2376,
    "name": "技嘉",
    "DividendRecentAvg": 0,
    "DividendRecentSlope": null,
    "Category": "電腦週邊",
    "CurrentClosingPrice": 292.5,
    "CurrentTrend": -9.5,
    "CurrentTrendPercent": -0.0315,
    "CurrentTurnover": 13104,
    "CurrentPE": 39.21,
    "CurrentPEAvg": 119.56,
    "CurrentRecentTrendPercent": 0.0503,
    "CurrentRecentTrendComment": "連2跌",
    "URL": "https://tw.stock.yahoo.com/quote/2376/dividend"
  },
  {
    "id": 2882,
    "name": "國泰金",
    "DividendRecentAvg": 0,
    "DividendRecentSlope": 0,
    "Category": "金融業",
    "CurrentClosingPrice": 47.45,
    "CurrentTrend": -1,
    "CurrentTrendPercent": -0.0206,
    "CurrentTurnover": 30936,
    "CurrentPE": 15.11,
    "CurrentPEAvg": 14.1,
    "CurrentRecentTrendPercent": 0.0206,
    "CurrentRecentTrendComment": "連2漲→跌",
    "URL": "https://tw.stock.yahoo.com/quote/2882/dividend"
  },
  {
    "id": 2377,
    "name": "微星",
    "DividendRecentAvg": 0,
    "DividendRecentSlope": null,
    "Category": "電腦週邊",
    "CurrentClosingPrice": 154,
    "CurrentTrend": -7,
    "CurrentTrendPercent": -0.0435,
    "CurrentTurnover": 7144,
    "CurrentPE": 17.26,
    "CurrentPEAvg": 119.56,
    "CurrentRecentTrendPercent": 0.0464,
    "CurrentRecentTrendComment": "連2跌",
    "URL": "https://tw.stock.yahoo.com/quote/2377/dividend"
  },
  {
    "id": 3005,
    "name": "神基",
    "DividendRecentAvg": 0,
    "DividendRecentSlope": 0,
    "Category": "電腦週邊",
    "CurrentClosingPrice": 107,
    "CurrentTrend": -1.5,
    "CurrentTrendPercent": -0.0138,
    "CurrentTurnover": 10054,
    "CurrentPE": 17.43,
    "CurrentPEAvg": 119.56,
    "CurrentRecentTrendPercent": 0.036,
    "CurrentRecentTrendComment": "連2跌",
    "URL": "https://tw.stock.yahoo.com/quote/3005/dividend"
  },
  {
    "id": 6278,
    "name": "台表科",
    "DividendRecentAvg": 0,
    "DividendRecentSlope": null,
    "Category": "光電",
    "CurrentClosingPrice": 107.5,
    "CurrentTrend": -1.5,
    "CurrentTrendPercent": -0.0138,
    "CurrentTurnover": 2699,
    "CurrentPE": 12.54,
    "CurrentPEAvg": 38.75,
    "CurrentRecentTrendPercent": 0.0138,
    "CurrentRecentTrendComment": "連2漲→跌",
    "URL": "https://tw.stock.yahoo.com/quote/6278/dividend"
  },
  {
    "id": 1216,
    "name": "統一",
    "DividendRecentAvg": 0,
    "DividendRecentSlope": null,
    "Category": "食品",
    "CurrentClosingPrice": 76,
    "CurrentTrend": -0.8,
    "CurrentTrendPercent": -0.0104,
    "CurrentTurnover": 11518,
    "CurrentPE": 23.53,
    "CurrentPEAvg": 43.4,
    "CurrentRecentTrendPercent": 0.0104,
    "CurrentRecentTrendComment": "連2漲→跌",
    "URL": "https://tw.stock.yahoo.com/quote/1216/dividend"
  },
  {
    "id": 1504,
    "name": "東元",
    "DividendRecentAvg": 0,
    "DividendRecentSlope": null,
    "Category": "電機機械",
    "CurrentClosingPrice": 59.9,
    "CurrentTrend": -1.1,
    "CurrentTrendPercent": -0.018,
    "CurrentTurnover": 71684,
    "CurrentPE": 21.7,
    "CurrentPEAvg": 92.57,
    "CurrentRecentTrendPercent": 0.0196,
    "CurrentRecentTrendComment": "連2跌",
    "URL": "https://tw.stock.yahoo.com/quote/1504/dividend"
  },
  {
    "id": 2383,
    "name": "台光電",
    "DividendRecentAvg": 0,
    "DividendRecentSlope": null,
    "Category": "電子零組件",
    "CurrentClosingPrice": 375.5,
    "CurrentTrend": -9.5,
    "CurrentTrendPercent": -0.0247,
    "CurrentTurnover": 8200,
    "CurrentPE": 23.48,
    "CurrentPEAvg": 45.51,
    "CurrentRecentTrendPercent": 0.0247,
    "CurrentRecentTrendComment": "漲→跌",
    "URL": "https://tw.stock.yahoo.com/quote/2383/dividend"
  },
  {
    "id": 3023,
    "name": "信邦",
    "DividendRecentAvg": 0,
    "DividendRecentSlope": null,
    "Category": "電子零組件",
    "CurrentClosingPrice": 279,
    "CurrentTrend": 4,
    "CurrentTrendPercent": 0.0145,
    "CurrentTurnover": 2123,
    "CurrentPE": 20.28,
    "CurrentPEAvg": 45.51,
    "CurrentRecentTrendPercent": 0.0295,
    "CurrentRecentTrendComment": "連2漲",
    "URL": "https://tw.stock.yahoo.com/quote/3023/dividend"
  },
  {
    "id": 6285,
    "name": "啟碁",
    "DividendRecentAvg": 0,
    "DividendRecentSlope": null,
    "Category": "通訊網路",
    "CurrentClosingPrice": 147,
    "CurrentTrend": -1,
    "CurrentTrendPercent": -0.0068,
    "CurrentTurnover": 6597,
    "CurrentPE": 18.73,
    "CurrentPEAvg": 85.1,
    "CurrentRecentTrendPercent": 0.0068,
    "CurrentRecentTrendComment": "漲→跌",
    "URL": "https://tw.stock.yahoo.com/quote/6285/dividend"
  },
  {
    "id": 1301,
    "name": "台塑",
    "DividendRecentAvg": 0,
    "DividendRecentSlope": null,
    "Category": "塑膠",
    "CurrentClosingPrice": 67.1,
    "CurrentTrend": -1,
    "CurrentTrendPercent": -0.0147,
    "CurrentTurnover": 12793,
    "CurrentPE": 58.35,
    "CurrentPEAvg": 45.03,
    "CurrentRecentTrendPercent": 0.0147,
    "CurrentRecentTrendComment": "漲→跌",
    "URL": "https://tw.stock.yahoo.com/quote/1301/dividend"
  },
  {
    "id": 1605,
    "name": "華新",
    "DividendRecentAvg": 0,
    "DividendRecentSlope": null,
    "Category": "電器電纜",
    "CurrentClosingPrice": 38.85,
    "CurrentTrend": -1.55,
    "CurrentTrendPercent": -0.0384,
    "CurrentTurnover": 76753,
    "CurrentPE": 30.59,
    "CurrentPEAvg": 47.77,
    "CurrentRecentTrendPercent": 0.0384,
    "CurrentRecentTrendComment": "連2漲→跌",
    "URL": "https://tw.stock.yahoo.com/quote/1605/dividend"
  },
  {
    "id": 2385,
    "name": "群光",
    "DividendRecentAvg": 0,
    "DividendRecentSlope": null,
    "Category": "電子零組件",
    "CurrentClosingPrice": 199,
    "CurrentTrend": -7.5,
    "CurrentTrendPercent": -0.0363,
    "CurrentTurnover": 7245,
    "CurrentPE": 19.32,
    "CurrentPEAvg": 45.51,
    "CurrentRecentTrendPercent": 0.0363,
    "CurrentRecentTrendComment": "連2漲→跌",
    "URL": "https://tw.stock.yahoo.com/quote/2385/dividend"
  },
  {
    "id": 3037,
    "name": "欣興",
    "DividendRecentAvg": 0,
    "DividendRecentSlope": null,
    "Category": "電子零組件",
    "CurrentClosingPrice": 170,
    "CurrentTrend": -8.5,
    "CurrentTrendPercent": -0.0476,
    "CurrentTurnover": 21153,
    "CurrentPE": 21.63,
    "CurrentPEAvg": 45.51,
    "CurrentRecentTrendPercent": 0.0503,
    "CurrentRecentTrendComment": "連2跌",
    "URL": "https://tw.stock.yahoo.com/quote/3037/dividend"
  },
  {
    "id": 1303,
    "name": "南亞",
    "DividendRecentAvg": 0,
    "DividendRecentSlope": null,
    "Category": "塑膠",
    "CurrentClosingPrice": 55,
    "CurrentTrend": -0.8,
    "CurrentTrendPercent": -0.0143,
    "CurrentTurnover": 11102,
    "CurrentPE": 68.75,
    "CurrentPEAvg": 45.03,
    "CurrentRecentTrendPercent": 0.0143,
    "CurrentRecentTrendComment": "漲→跌",
    "URL": "https://tw.stock.yahoo.com/quote/1303/dividend"
  },
  {
    "id": 1717,
    "name": "長興",
    "DividendRecentAvg": 0,
    "DividendRecentSlope": 0,
    "Category": "化學",
    "CurrentClosingPrice": 30.5,
    "CurrentTrend": -0.65,
    "CurrentTrendPercent": -0.0209,
    "CurrentTurnover": 3661,
    "CurrentPE": 23.83,
    "CurrentPEAvg": 30.2,
    "CurrentRecentTrendPercent": 0.0256,
    "CurrentRecentTrendComment": "連2跌",
    "URL": "https://tw.stock.yahoo.com/quote/1717/dividend"
  },
  {
    "id": 2404,
    "name": "漢唐",
    "DividendRecentAvg": 0,
    "DividendRecentSlope": null,
    "Category": "其他電子",
    "CurrentClosingPrice": 399.5,
    "CurrentTrend": -18.5,
    "CurrentTrendPercent": -0.0443,
    "CurrentTurnover": 4910,
    "CurrentPE": 16.1,
    "CurrentPEAvg": 24.08,
    "CurrentRecentTrendPercent": 0.0752,
    "CurrentRecentTrendComment": "連2跌",
    "URL": "https://tw.stock.yahoo.com/quote/2404/dividend"
  },
  {
    "id": 3044,
    "name": "健鼎",
    "DividendRecentAvg": 0,
    "DividendRecentSlope": 0,
    "Category": "電子零組件",
    "CurrentClosingPrice": 193.5,
    "CurrentTrend": -4.5,
    "CurrentTrendPercent": -0.0227,
    "CurrentTurnover": 6158,
    "CurrentPE": 16.78,
    "CurrentPEAvg": 45.51,
    "CurrentRecentTrendPercent": 0.0227,
    "CurrentRecentTrendComment": "連2漲→跌",
    "URL": "https://tw.stock.yahoo.com/quote/3044/dividend"
  },
  {
    "id": 6456,
    "name": "GIS-KY",
    "DividendRecentAvg": 0,
    "DividendRecentSlope": 0,
    "Category": "光電",
    "CurrentClosingPrice": 56.4,
    "CurrentTrend": -1.5,
    "CurrentTrendPercent": -0.0259,
    "CurrentTurnover": 1230,
    "CurrentPE": 0,
    "CurrentPEAvg": 0,
    "CurrentRecentTrendPercent": 0.0293,
    "CurrentRecentTrendComment": "連2跌",
    "URL": "https://tw.stock.yahoo.com/quote/6456/dividend"
  },
  {
    "id": 1326,
    "name": "台化",
    "DividendRecentAvg": 0,
    "DividendRecentSlope": null,
    "Category": "塑膠",
    "CurrentClosingPrice": 52.4,
    "CurrentTrend": -1.2,
    "CurrentTrendPercent": -0.0224,
    "CurrentTurnover": 12772,
    "CurrentPE": 35.89,
    "CurrentPEAvg": 45.03,
    "CurrentRecentTrendPercent": 0.0224,
    "CurrentRecentTrendComment": "平→跌",
    "URL": "https://tw.stock.yahoo.com/quote/1326/dividend"
  },
  {
    "id": 1722,
    "name": "台肥",
    "DividendRecentAvg": 0,
    "DividendRecentSlope": null,
    "Category": "化學",
    "CurrentClosingPrice": 62.4,
    "CurrentTrend": 0.2,
    "CurrentTrendPercent": 0.0032,
    "CurrentTurnover": 6547,
    "CurrentPE": 15.6,
    "CurrentPEAvg": 30.2,
    "CurrentRecentTrendPercent": 0.013,
    "CurrentRecentTrendComment": "連2漲",
    "URL": "https://tw.stock.yahoo.com/quote/1722/dividend"
  },
  {
    "id": 2409,
    "name": "友達",
    "DividendRecentAvg": 0,
    "DividendRecentSlope": null,
    "Category": "光電",
    "CurrentClosingPrice": 17.15,
    "CurrentTrend": -0.5,
    "CurrentTrendPercent": -0.0283,
    "CurrentTurnover": 57089,
    "CurrentPE": 0,
    "CurrentPEAvg": 0,
    "CurrentRecentTrendPercent": 0.0283,
    "CurrentRecentTrendComment": "漲→跌",
    "URL": "https://tw.stock.yahoo.com/quote/2409/dividend"
  },
  {
    "id": 3189,
    "name": "景碩",
    "DividendRecentAvg": 0,
    "DividendRecentSlope": null,
    "Category": "半導體",
    "CurrentClosingPrice": 94,
    "CurrentTrend": -1.8,
    "CurrentTrendPercent": -0.0188,
    "CurrentTurnover": 3880,
    "CurrentPE": 940,
    "CurrentPEAvg": 69.96,
    "CurrentRecentTrendPercent": 0.0359,
    "CurrentRecentTrendComment": "連2跌",
    "URL": "https://tw.stock.yahoo.com/quote/3189/dividend"
  },
  {
    "id": 6531,
    "name": "愛普",
    "DividendRecentAvg": 0,
    "DividendRecentSlope": null,
    "Category": "半導體",
    "CurrentClosingPrice": 360.5,
    "CurrentTrend": -22.5,
    "CurrentTrendPercent": -0.0587,
    "CurrentTurnover": 4375,
    "CurrentPE": 40.41,
    "CurrentPEAvg": 69.96,
    "CurrentRecentTrendPercent": 0.0587,
    "CurrentRecentTrendComment": "平→跌",
    "URL": "https://tw.stock.yahoo.com/quote/6531/dividend"
  },
  {
    "id": 1402,
    "name": "遠東新",
    "DividendRecentAvg": 0,
    "DividendRecentSlope": null,
    "Category": "紡織",
    "CurrentClosingPrice": 31.15,
    "CurrentTrend": -0.65,
    "CurrentTrendPercent": -0.0204,
    "CurrentTurnover": 9308,
    "CurrentPE": 20.23,
    "CurrentPEAvg": 45.71,
    "CurrentRecentTrendPercent": 0.025,
    "CurrentRecentTrendComment": "連2跌",
    "URL": "https://tw.stock.yahoo.com/quote/1402/dividend"
  },
  {
    "id": 2891,
    "name": "中信金",
    "DividendRecentAvg": 0,
    "DividendRecentSlope": 0,
    "Category": "金融業",
    "CurrentClosingPrice": 31,
    "CurrentTrend": -0.7,
    "CurrentTrendPercent": -0.0221,
    "CurrentTurnover": 65383,
    "CurrentPE": 11.11,
    "CurrentPEAvg": 14.1,
    "CurrentRecentTrendPercent": 0.0221,
    "CurrentRecentTrendComment": "連2漲→跌",
    "URL": "https://tw.stock.yahoo.com/quote/2891/dividend"
  },
  {
    "id": 1802,
    "name": "台玻",
    "DividendRecentAvg": 0,
    "DividendRecentSlope": -999,
    "Category": "",
    "CurrentClosingPrice": 0,
    "CurrentTurnover": 0,
    "CurrentPEAvg": 0,
    "URL": "https://tw.stock.yahoo.com/quote/1802/dividend"
  },
  {
    "id": 2441,
    "name": "超豐",
    "DividendRecentAvg": null,
    "DividendRecentSlope": null,
    "Category": "半導體",
    "CurrentClosingPrice": 59,
    "CurrentTrend": -1.7,
    "CurrentTrendPercent": -0.028,
    "CurrentTurnover": 1949,
    "CurrentPE": 16.81,
    "CurrentPEAvg": 69.96,
    "CurrentRecentTrendPercent": 0.0359,
    "CurrentRecentTrendComment": "連2跌",
    "URL": "https://tw.stock.yahoo.com/quote/2441/dividend"
  },
  {
    "id": 2301,
    "name": "光寶科",
    "DividendRecentAvg": 0.10826,
    "DividendRecentSlope": -0.0079,
    "Category": "電腦週邊",
    "CurrentClosingPrice": 96.1,
    "CurrentTrend": -2.9,
    "CurrentTrendPercent": -0.0293,
    "CurrentTurnover": 23737,
    "CurrentPE": 15.21,
    "CurrentPEAvg": 119.56,
    "CurrentRecentTrendPercent": 0.0293,
    "CurrentRecentTrendComment": "連2漲→跌",
    "URL": "https://tw.stock.yahoo.com/quote/2301/dividend"
  },
  {
    "id": 2474,
    "name": "可成",
    "DividendRecentAvg": 0.0736,
    "DividendRecentSlope": null,
    "Category": "其他電子",
    "CurrentClosingPrice": 207,
    "CurrentTrend": -1,
    "CurrentTrendPercent": -0.0048,
    "CurrentTurnover": 4042,
    "CurrentPE": 15.39,
    "CurrentPEAvg": 24.08,
    "CurrentRecentTrendPercent": 0.0048,
    "CurrentRecentTrendComment": "連2漲→跌",
    "URL": "https://tw.stock.yahoo.com/quote/2474/dividend"
  },
  {
    "id": 2330,
    "name": "台積電",
    "DividendRecentAvg": 0.049,
    "DividendRecentSlope": -0.0113,
    "Category": "半導體",
    "CurrentClosingPrice": 750,
    "CurrentTrend": -54,
    "CurrentTrendPercent": -0.0672,
    "CurrentTurnover": 130830,
    "CurrentPE": 23.2,
    "CurrentPEAvg": 69.96,
    "CurrentRecentTrendPercent": 0.0672,
    "CurrentRecentTrendComment": "平→跌",
    "URL": "https://tw.stock.yahoo.com/quote/2330/dividend"
  },
  {
    "id": 2382,
    "name": "廣達",
    "DividendRecentAvg": 0.03952,
    "DividendRecentSlope": 0.00632,
    "Category": "電腦週邊",
    "CurrentClosingPrice": 241.5,
    "CurrentTrend": -9,
    "CurrentTrendPercent": -0.0359,
    "CurrentTurnover": 36104,
    "CurrentPE": 23.47,
    "CurrentPEAvg": 119.56,
    "CurrentRecentTrendPercent": 0.0511,
    "CurrentRecentTrendComment": "連2跌",
    "URL": "https://tw.stock.yahoo.com/quote/2382/dividend"
  },
  {
    "id": 2327,
    "name": "國巨",
    "DividendRecentAvg": 0.03928,
    "DividendRecentSlope": null,
    "Category": "電子零組件",
    "CurrentClosingPrice": 588,
    "CurrentTrend": -5,
    "CurrentTrendPercent": -0.0084,
    "CurrentTurnover": 3779,
    "CurrentPE": 14.11,
    "CurrentPEAvg": 45.51,
    "CurrentRecentTrendPercent": 0.0084,
    "CurrentRecentTrendComment": "平→跌",
    "URL": "https://tw.stock.yahoo.com/quote/2327/dividend"
  },
  {
    "id": 2344,
    "name": "華邦電",
    "DividendRecentAvg": 0.0322,
    "DividendRecentSlope": 0.007125,
    "Category": "半導體",
    "CurrentClosingPrice": 25.4,
    "CurrentTrend": -0.5,
    "CurrentTrendPercent": -0.0193,
    "CurrentTurnover": 37202,
    "CurrentPE": 0,
    "CurrentPEAvg": 0,
    "CurrentRecentTrendPercent": 0.025,
    "CurrentRecentTrendComment": "連2跌",
    "URL": "https://tw.stock.yahoo.com/quote/2344/dividend"
  },
  {
    "id": 9945,
    "name": "潤泰新",
    "DividendRecentAvg": 0.028,
    "DividendRecentSlope": null,
    "Category": "其他",
    "CurrentClosingPrice": 36.15,
    "CurrentTrend": -0.3,
    "CurrentTrendPercent": -0.0082,
    "CurrentTurnover": 14512,
    "CurrentPE": 13.24,
    "CurrentPEAvg": 22.81,
    "CurrentRecentTrendPercent": 0.0082,
    "CurrentRecentTrendComment": "連2漲→跌",
    "URL": "https://tw.stock.yahoo.com/quote/9945/dividend"
  },
  {
    "id": 3406,
    "name": "玉晶光",
    "DividendRecentAvg": 0.0276,
    "DividendRecentSlope": null,
    "Category": "光電",
    "CurrentClosingPrice": 424,
    "CurrentTrend": -18,
    "CurrentTrendPercent": -0.0407,
    "CurrentTurnover": 1477,
    "CurrentPE": 15.56,
    "CurrentPEAvg": 38.75,
    "CurrentRecentTrendPercent": 0.0525,
    "CurrentRecentTrendComment": "連2跌",
    "URL": "https://tw.stock.yahoo.com/quote/3406/dividend"
  },
  {
    "id": 2454,
    "name": "聯發科",
    "DividendRecentAvg": 0.02236,
    "DividendRecentSlope": 0.01108,
    "Category": "半導體",
    "CurrentClosingPrice": 993,
    "CurrentTrend": -57,
    "CurrentTrendPercent": -0.0543,
    "CurrentTurnover": 15649,
    "CurrentPE": 20.53,
    "CurrentPEAvg": 69.96,
    "CurrentRecentTrendPercent": 0.0543,
    "CurrentRecentTrendComment": "平→跌",
    "URL": "https://tw.stock.yahoo.com/quote/2454/dividend"
  },
  {
    "id": 1229,
    "name": "聯華",
    "DividendRecentAvg": 0.01466,
    "DividendRecentSlope": null,
    "Category": "食品",
    "CurrentClosingPrice": 65.3,
    "CurrentTrend": -0.8,
    "CurrentTrendPercent": -0.0121,
    "CurrentTurnover": 2175,
    "CurrentPE": 24.73,
    "CurrentPEAvg": 43.4,
    "CurrentRecentTrendPercent": 0.0151,
    "CurrentRecentTrendComment": "連2跌",
    "URL": "https://tw.stock.yahoo.com/quote/1229/dividend"
  },
  {
    "id": 3714,
    "name": "富采",
    "DividendRecentAvg": 0.01416,
    "DividendRecentSlope": null,
    "Category": "光電",
    "CurrentClosingPrice": 38.55,
    "CurrentTrend": -1.2,
    "CurrentTrendPercent": -0.0302,
    "CurrentTurnover": 2784,
    "CurrentPE": 0,
    "CurrentPEAvg": 0,
    "CurrentRecentTrendPercent": 0.0302,
    "CurrentRecentTrendComment": "連2漲→跌",
    "URL": "https://tw.stock.yahoo.com/quote/3714/dividend"
  },
  {
    "id": 9941,
    "name": "裕融",
    "DividendRecentAvg": 0.0124,
    "DividendRecentSlope": null,
    "Category": "其他",
    "CurrentClosingPrice": 146,
    "CurrentTrend": -2,
    "CurrentTrendPercent": -0.0135,
    "CurrentTurnover": 1717,
    "CurrentPE": 15.08,
    "CurrentPEAvg": 22.81,
    "CurrentRecentTrendPercent": 0.0135,
    "CurrentRecentTrendComment": "連2漲→跌",
    "URL": "https://tw.stock.yahoo.com/quote/9941/dividend"
  },
  {
    "id": 8454,
    "name": "富邦媒",
    "DividendRecentAvg": 0.012,
    "DividendRecentSlope": 0.0025,
    "Category": "數位雲端",
    "CurrentClosingPrice": 384.5,
    "CurrentTrend": -10.5,
    "CurrentTrendPercent": -0.0266,
    "CurrentTurnover": 1871,
    "CurrentPE": 25.46,
    "CurrentPEAvg": 57.73,
    "CurrentRecentTrendPercent": 0.0266,
    "CurrentRecentTrendComment": "連2漲→跌",
    "URL": "https://tw.stock.yahoo.com/quote/8454/dividend"
  },
  {
    "id": 9910,
    "name": "豐泰",
    "DividendRecentAvg": 0.0084,
    "DividendRecentSlope": null,
    "Category": "運動休閒",
    "CurrentClosingPrice": 153.5,
    "CurrentTrend": -5,
    "CurrentTrendPercent": -0.0315,
    "CurrentTurnover": 4665,
    "CurrentPE": 30.46,
    "CurrentPEAvg": 26.62,
    "CurrentRecentTrendPercent": 0.0315,
    "CurrentRecentTrendComment": "連2漲→跌",
    "URL": "https://tw.stock.yahoo.com/quote/9910/dividend"
  },
  {
    "id": 2834,
    "name": "臺企銀",
    "DividendRecentAvg": 0.0058,
    "DividendRecentSlope": null,
    "Category": "金融業",
    "CurrentClosingPrice": 16.15,
    "CurrentTrend": -0.05,
    "CurrentTrendPercent": -0.0031,
    "CurrentTurnover": 37485,
    "CurrentPE": 12.52,
    "CurrentPEAvg": 14.1,
    "CurrentRecentTrendPercent": 0.0031,
    "CurrentRecentTrendComment": "連2漲→跌",
    "URL": "https://tw.stock.yahoo.com/quote/2834/dividend"
  },
  {
    "id": 2812,
    "name": "台中銀",
    "DividendRecentAvg": 0.0056,
    "DividendRecentSlope": null,
    "Category": "金融業",
    "CurrentClosingPrice": 17.1,
    "CurrentTrend": -0.3,
    "CurrentTrendPercent": -0.0172,
    "CurrentTurnover": 10708,
    "CurrentPE": 13.05,
    "CurrentPEAvg": 14.1,
    "CurrentRecentTrendPercent": 0.0172,
    "CurrentRecentTrendComment": "連2漲→跌",
    "URL": "https://tw.stock.yahoo.com/quote/2812/dividend"
  },
  {
    "id": 3706,
    "name": "神達",
    "DividendRecentAvg": 0.0054,
    "DividendRecentSlope": -0.003,
    "Category": "電腦週邊",
    "CurrentClosingPrice": 43.7,
    "CurrentTrend": -1,
    "CurrentTrendPercent": -0.0224,
    "CurrentTurnover": 12795,
    "CurrentPE": 29.53,
    "CurrentPEAvg": 119.56,
    "CurrentRecentTrendPercent": 0.0289,
    "CurrentRecentTrendComment": "連2跌",
    "URL": "https://tw.stock.yahoo.com/quote/3706/dividend"
  },
  {
    "id": 2615,
    "name": "萬海",
    "DividendRecentAvg": 0.005,
    "DividendRecentSlope": null,
    "Category": "航運",
    "CurrentClosingPrice": 43.25,
    "CurrentTrend": 0.35,
    "CurrentTrendPercent": 0.0082,
    "CurrentTurnover": 13639,
    "CurrentPE": 0,
    "CurrentPEAvg": 0,
    "CurrentRecentTrendPercent": 0.0105,
    "CurrentRecentTrendComment": "連2漲",
    "URL": "https://tw.stock.yahoo.com/quote/2615/dividend"
  },
  {
    "id": 2027,
    "name": "大成鋼",
    "DividendRecentAvg": 0.0046,
    "DividendRecentSlope": null,
    "Category": "鋼鐵",
    "CurrentClosingPrice": 37.7,
    "CurrentTrend": -0.1,
    "CurrentTrendPercent": -0.0026,
    "CurrentTurnover": 16886,
    "CurrentPE": 15.14,
    "CurrentPEAvg": 45.28,
    "CurrentRecentTrendPercent": 0.0026,
    "CurrentRecentTrendComment": "連2漲→跌",
    "URL": "https://tw.stock.yahoo.com/quote/2027/dividend"
  },
  {
    "id": 5871,
    "name": "中租-KY",
    "DividendRecentAvg": 0.0042,
    "DividendRecentSlope": null,
    "Category": "其他",
    "CurrentClosingPrice": 168,
    "CurrentTrend": -4,
    "CurrentTrendPercent": -0.0233,
    "CurrentTurnover": 8596,
    "CurrentPE": 11.84,
    "CurrentPEAvg": 22.81,
    "CurrentRecentTrendPercent": 0.0233,
    "CurrentRecentTrendComment": "連2漲→跌",
    "URL": "https://tw.stock.yahoo.com/quote/5871/dividend"
  },
  {
    "id": 6592,
    "name": "和潤企業",
    "DividendRecentAvg": 0.004,
    "DividendRecentSlope": null,
    "Category": "其他",
    "CurrentClosingPrice": 115.5,
    "CurrentTrend": -1.5,
    "CurrentTrendPercent": -0.0128,
    "CurrentTurnover": 1163,
    "CurrentPE": 20.85,
    "CurrentPEAvg": 22.81,
    "CurrentRecentTrendPercent": 0.0415,
    "CurrentRecentTrendComment": "連4跌",
    "URL": "https://tw.stock.yahoo.com/quote/6592/dividend"
  },
  {
    "id": 2395,
    "name": "研華",
    "DividendRecentAvg": 0.004,
    "DividendRecentSlope": null,
    "Category": "電腦週邊",
    "CurrentClosingPrice": 365,
    "CurrentTrend": -7,
    "CurrentTrendPercent": -0.0188,
    "CurrentTurnover": 1192,
    "CurrentPE": 28.92,
    "CurrentPEAvg": 119.56,
    "CurrentRecentTrendPercent": 0.0188,
    "CurrentRecentTrendComment": "連2漲→跌",
    "URL": "https://tw.stock.yahoo.com/quote/2395/dividend"
  },
  {
    "id": 1210,
    "name": "大成",
    "DividendRecentAvg": 0.0026,
    "DividendRecentSlope": null,
    "Category": "食品",
    "CurrentClosingPrice": 55.5,
    "CurrentTrend": -0.2,
    "CurrentTrendPercent": -0.0036,
    "CurrentTurnover": 5230,
    "CurrentPE": 11.54,
    "CurrentPEAvg": 43.4,
    "CurrentRecentTrendPercent": 0.0036,
    "CurrentRecentTrendComment": "連2漲→跌",
    "URL": "https://tw.stock.yahoo.com/quote/1210/dividend"
  },
  {
    "id": 2801,
    "name": "彰銀",
    "DividendRecentAvg": 0.0026,
    "DividendRecentSlope": null,
    "Category": "金融業",
    "CurrentClosingPrice": 17.85,
    "CurrentTrend": -0.05,
    "CurrentTrendPercent": -0.0028,
    "CurrentTurnover": 23001,
    "CurrentPE": 14.88,
    "CurrentPEAvg": 14.1,
    "CurrentRecentTrendPercent": 0.0028,
    "CurrentRecentTrendComment": "漲→跌",
    "URL": "https://tw.stock.yahoo.com/quote/2801/dividend"
  },
  {
    "id": 2889,
    "name": "國票金",
    "DividendRecentAvg": 0.0024,
    "DividendRecentSlope": null,
    "Category": "金融業",
    "CurrentClosingPrice": 13.6,
    "CurrentTrend": 0.15,
    "CurrentTrendPercent": 0.0112,
    "CurrentTurnover": 12070,
    "CurrentPE": 23.45,
    "CurrentPEAvg": 14.1,
    "CurrentRecentTrendPercent": 0.0112,
    "CurrentRecentTrendComment": "連7跌→漲",
    "URL": "https://tw.stock.yahoo.com/quote/2889/dividend"
  },
  {
    "id": 2845,
    "name": "遠東銀",
    "DividendRecentAvg": 0.0022,
    "DividendRecentSlope": null,
    "Category": "金融業",
    "CurrentClosingPrice": 14.5,
    "CurrentTrend": 0.05,
    "CurrentTrendPercent": 0.0035,
    "CurrentTurnover": 12664,
    "CurrentPE": 14.08,
    "CurrentPEAvg": 14.1,
    "CurrentRecentTrendPercent": 0.0175,
    "CurrentRecentTrendComment": "連2漲",
    "URL": "https://tw.stock.yahoo.com/quote/2845/dividend"
  },
  {
    "id": 2892,
    "name": "第一金",
    "DividendRecentAvg": 0.002,
    "DividendRecentSlope": 0.0005,
    "Category": "金融業",
    "CurrentClosingPrice": 26.65,
    "CurrentTrend": -0.25,
    "CurrentTrendPercent": -0.0093,
    "CurrentTurnover": 27333,
    "CurrentPE": 16.15,
    "CurrentPEAvg": 14.1,
    "CurrentRecentTrendPercent": 0.0093,
    "CurrentRecentTrendComment": "平→跌",
    "URL": "https://tw.stock.yahoo.com/quote/2892/dividend"
  },
  {
    "id": 3653,
    "name": "健策",
    "DividendRecentAvg": 0.002,
    "DividendRecentSlope": null,
    "Category": "電子零組件",
    "CurrentClosingPrice": 907,
    "CurrentTrend": -29,
    "CurrentTrendPercent": -0.031,
    "CurrentTurnover": 1284,
    "CurrentPE": 55.58,
    "CurrentPEAvg": 45.51,
    "CurrentRecentTrendPercent": 0.031,
    "CurrentRecentTrendComment": "連2漲→跌",
    "URL": "https://tw.stock.yahoo.com/quote/3653/dividend"
  },
  {
    "id": 2049,
    "name": "上銀",
    "DividendRecentAvg": 0.0018,
    "DividendRecentSlope": null,
    "Category": "電機機械",
    "CurrentClosingPrice": 228.5,
    "CurrentTrend": -11,
    "CurrentTrendPercent": -0.0459,
    "CurrentTurnover": 5468,
    "CurrentPE": 39.74,
    "CurrentPEAvg": 92.57,
    "CurrentRecentTrendPercent": 0.0459,
    "CurrentRecentTrendComment": "漲→跌",
    "URL": "https://tw.stock.yahoo.com/quote/2049/dividend"
  },
  {
    "id": 2618,
    "name": "長榮航",
    "DividendRecentAvg": 0.0006,
    "DividendRecentSlope": null,
    "Category": "航運",
    "CurrentClosingPrice": 31.1,
    "CurrentTrend": -0.4,
    "CurrentTrendPercent": -0.0127,
    "CurrentTurnover": 76211,
    "CurrentPE": 7.78,
    "CurrentPEAvg": 26.05,
    "CurrentRecentTrendPercent": 0.0127,
    "CurrentRecentTrendComment": "漲→跌",
    "URL": "https://tw.stock.yahoo.com/quote/2618/dividend"
  },
  {
    "id": 2890,
    "name": "永豐金",
    "DividendRecentAvg": 0.0006,
    "DividendRecentSlope": 0.0005,
    "Category": "金融業",
    "CurrentClosingPrice": 21.2,
    "CurrentTrend": -0.45,
    "CurrentTrendPercent": -0.0208,
    "CurrentTurnover": 35134,
    "CurrentPE": 13.25,
    "CurrentPEAvg": 14.1,
    "CurrentRecentTrendPercent": 0.0208,
    "CurrentRecentTrendComment": "連2漲→跌",
    "URL": "https://tw.stock.yahoo.com/quote/2890/dividend"
  },
  {
    "id": 2207,
    "name": "和泰車",
    "DividendRecentAvg": 0.0004,
    "DividendRecentSlope": null,
    "Category": "汽車",
    "CurrentClosingPrice": 601,
    "CurrentTrend": -5,
    "CurrentTrendPercent": -0.0083,
    "CurrentTurnover": 819,
    "CurrentPE": 14.65,
    "CurrentPEAvg": 50.73,
    "CurrentRecentTrendPercent": 0.0083,
    "CurrentRecentTrendComment": "平→跌",
    "URL": "https://tw.stock.yahoo.com/quote/2207/dividend"
  },
  {
    "id": 3665,
    "name": "貿聯-KY",
    "DividendRecentAvg": 0.0002,
    "DividendRecentSlope": null,
    "Category": "其他電子",
    "CurrentClosingPrice": 226.5,
    "CurrentTrend": -7,
    "CurrentTrendPercent": -0.03,
    "CurrentTurnover": 1430,
    "CurrentPE": 15.96,
    "CurrentPEAvg": 24.08,
    "CurrentRecentTrendPercent": 0.0382,
    "CurrentRecentTrendComment": "連2跌",
    "URL": "https://tw.stock.yahoo.com/quote/3665/dividend"
  },
  {
    "id": 3231,
    "name": "緯創",
    "DividendRecentAvg": 0,
    "DividendRecentSlope": null,
    "Category": "電腦週邊",
    "CurrentClosingPrice": 115,
    "CurrentTrend": -3,
    "CurrentTrendPercent": -0.0254,
    "CurrentTurnover": 78541,
    "CurrentPE": 28.75,
    "CurrentPEAvg": 119.56,
    "CurrentRecentTrendPercent": 0.0254,
    "CurrentRecentTrendComment": "連2漲→跌",
    "URL": "https://tw.stock.yahoo.com/quote/3231/dividend"
  },
  {
    "id": 1590,
    "name": "亞德客-KY",
    "DividendRecentAvg": 0,
    "DividendRecentSlope": null,
    "Category": "電機機械",
    "CurrentClosingPrice": 1055,
    "CurrentTrend": -55,
    "CurrentTrendPercent": -0.0495,
    "CurrentTurnover": 882,
    "CurrentPE": 30.29,
    "CurrentPEAvg": 92.57,
    "CurrentRecentTrendPercent": 0.0538,
    "CurrentRecentTrendComment": "連2跌",
    "URL": "https://tw.stock.yahoo.com/quote/1590/dividend"
  },
  {
    "id": 1907,
    "name": "永豐餘",
    "DividendRecentAvg": 0,
    "DividendRecentSlope": null,
    "Category": "造紙",
    "CurrentClosingPrice": 29.4,
    "CurrentTrend": -0.65,
    "CurrentTrendPercent": -0.0216,
    "CurrentTurnover": 2596,
    "CurrentPE": 26.73,
    "CurrentPEAvg": 65.33,
    "CurrentRecentTrendPercent": 0.0216,
    "CurrentRecentTrendComment": "連2漲→跌",
    "URL": "https://tw.stock.yahoo.com/quote/1907/dividend"
  },
  {
    "id": 2449,
    "name": "京元電子",
    "DividendRecentAvg": 0,
    "DividendRecentSlope": null,
    "Category": "半導體",
    "CurrentClosingPrice": 99,
    "CurrentTrend": -3,
    "CurrentTrendPercent": -0.0294,
    "CurrentTurnover": 20926,
    "CurrentPE": 20.71,
    "CurrentPEAvg": 69.96,
    "CurrentRecentTrendPercent": 0.0341,
    "CurrentRecentTrendComment": "連2跌",
    "URL": "https://tw.stock.yahoo.com/quote/2449/dividend"
  },
  {
    "id": 2002,
    "name": "中鋼",
    "DividendRecentAvg": 0,
    "DividendRecentSlope": -999,
    "Category": "",
    "CurrentClosingPrice": 0,
    "CurrentTurnover": 0,
    "CurrentPEAvg": 0,
    "URL": "https://tw.stock.yahoo.com/quote/2002/dividend"
  },
  {
    "id": 2912,
    "name": "統一超",
    "DividendRecentAvg": 0,
    "DividendRecentSlope": null,
    "Category": "貿易百貨",
    "CurrentClosingPrice": 270,
    "CurrentTrend": -1.5,
    "CurrentTrendPercent": -0.0055,
    "CurrentTurnover": 1855,
    "CurrentPE": 26.44,
    "CurrentPEAvg": 30.95,
    "CurrentRecentTrendPercent": 0.0092,
    "CurrentRecentTrendComment": "連2跌",
    "URL": "https://tw.stock.yahoo.com/quote/2912/dividend"
  },
  {
    "id": 3443,
    "name": "創意",
    "DividendRecentAvg": 0,
    "DividendRecentSlope": null,
    "Category": "半導體",
    "CurrentClosingPrice": 1155,
    "CurrentTrend": -60,
    "CurrentTrendPercent": -0.0494,
    "CurrentTurnover": 3238,
    "CurrentPE": 44.13,
    "CurrentPEAvg": 69.96,
    "CurrentRecentTrendPercent": 0.0494,
    "CurrentRecentTrendComment": "連3漲→跌",
    "URL": "https://tw.stock.yahoo.com/quote/3443/dividend"
  },
  {
    "id": 8464,
    "name": "億豐",
    "DividendRecentAvg": 0,
    "DividendRecentSlope": null,
    "Category": "居家生活",
    "CurrentClosingPrice": 365,
    "CurrentTrend": -3.5,
    "CurrentTrendPercent": -0.0095,
    "CurrentTurnover": 959,
    "CurrentPE": 19.49,
    "CurrentPEAvg": 17.67,
    "CurrentRecentTrendPercent": 0.0095,
    "CurrentRecentTrendComment": "連4漲→跌",
    "URL": "https://tw.stock.yahoo.com/quote/8464/dividend"
  },
  {
    "id": 2105,
    "name": "正新",
    "DividendRecentAvg": 0,
    "DividendRecentSlope": null,
    "Category": "橡膠",
    "CurrentClosingPrice": 46.9,
    "CurrentTrend": -0.95,
    "CurrentTrendPercent": -0.0199,
    "CurrentTurnover": 7480,
    "CurrentPE": 21.13,
    "CurrentPEAvg": 58.25,
    "CurrentRecentTrendPercent": 0.0516,
    "CurrentRecentTrendComment": "連4跌",
    "URL": "https://tw.stock.yahoo.com/quote/2105/dividend"
  },
  {
    "id": 2492,
    "name": "華新科",
    "DividendRecentAvg": 0,
    "DividendRecentSlope": null,
    "Category": "電子零組件",
    "CurrentClosingPrice": 104,
    "CurrentTrend": -2.5,
    "CurrentTrendPercent": -0.0235,
    "CurrentTurnover": 3928,
    "CurrentPE": 25.43,
    "CurrentPEAvg": 45.51,
    "CurrentRecentTrendPercent": 0.0235,
    "CurrentRecentTrendComment": "連2漲→跌",
    "URL": "https://tw.stock.yahoo.com/quote/2492/dividend"
  },
  {
    "id": 3481,
    "name": "群創",
    "DividendRecentAvg": 0,
    "DividendRecentSlope": -999,
    "Category": "",
    "CurrentClosingPrice": 0,
    "CurrentTurnover": 0,
    "CurrentPEAvg": 0,
    "URL": "https://tw.stock.yahoo.com/quote/3481/dividend"
  },
  {
    "id": 9904,
    "name": "寶成",
    "DividendRecentAvg": 0,
    "DividendRecentSlope": null,
    "Category": "運動休閒",
    "CurrentClosingPrice": 35.3,
    "CurrentTrend": -0.3,
    "CurrentTrendPercent": -0.0084,
    "CurrentTurnover": 18365,
    "CurrentPE": 9.81,
    "CurrentPEAvg": 26.62,
    "CurrentRecentTrendPercent": 0.0084,
    "CurrentRecentTrendComment": "連2漲→跌",
    "URL": "https://tw.stock.yahoo.com/quote/9904/dividend"
  },
  {
    "id": 3034,
    "name": "聯詠",
    "DividendRecentAvg": 0,
    "DividendRecentSlope": null,
    "Category": "半導體",
    "CurrentClosingPrice": 588,
    "CurrentTrend": -27,
    "CurrentTrendPercent": -0.0439,
    "CurrentTurnover": 7376,
    "CurrentPE": 15.34,
    "CurrentPEAvg": 69.96,
    "CurrentRecentTrendPercent": 0.0531,
    "CurrentRecentTrendComment": "連2跌",
    "URL": "https://tw.stock.yahoo.com/quote/3034/dividend"
  },
  {
    "id": 2059,
    "name": "川湖",
    "DividendRecentAvg": 0,
    "DividendRecentSlope": null,
    "Category": "電子零組件",
    "CurrentClosingPrice": 1230,
    "CurrentTrend": -60,
    "CurrentTrendPercent": -0.0465,
    "CurrentTurnover": 2814,
    "CurrentPE": 43.34,
    "CurrentPEAvg": 45.51,
    "CurrentRecentTrendPercent": 0.0465,
    "CurrentRecentTrendComment": "漲→跌",
    "URL": "https://tw.stock.yahoo.com/quote/2059/dividend"
  },
  {
    "id": 3532,
    "name": "台勝科",
    "DividendRecentAvg": 0,
    "DividendRecentSlope": null,
    "Category": "半導體",
    "CurrentClosingPrice": 164.5,
    "CurrentTrend": -9.5,
    "CurrentTrendPercent": -0.0546,
    "CurrentTurnover": 2051,
    "CurrentPE": 18.44,
    "CurrentPEAvg": 69.96,
    "CurrentRecentTrendPercent": 0.0546,
    "CurrentRecentTrendComment": "連2漲→跌",
    "URL": "https://tw.stock.yahoo.com/quote/3532/dividend"
  },
  {
    "id": 9914,
    "name": "美利達",
    "DividendRecentAvg": 0,
    "DividendRecentSlope": null,
    "Category": "運動休閒",
    "CurrentClosingPrice": 225.5,
    "CurrentTrend": -4.5,
    "CurrentTrendPercent": -0.0196,
    "CurrentTurnover": 1184,
    "CurrentPE": 39.84,
    "CurrentPEAvg": 26.62,
    "CurrentRecentTrendPercent": 0.0196,
    "CurrentRecentTrendComment": "平→跌",
    "URL": "https://tw.stock.yahoo.com/quote/9914/dividend"
  },
  {
    "id": 2303,
    "name": "聯電",
    "DividendRecentAvg": 0,
    "DividendRecentSlope": null,
    "Category": "半導體",
    "CurrentClosingPrice": 49.1,
    "CurrentTrend": -1.1,
    "CurrentTrendPercent": -0.0219,
    "CurrentTurnover": 125225,
    "CurrentPE": 10.08,
    "CurrentPEAvg": 69.96,
    "CurrentRecentTrendPercent": 0.0239,
    "CurrentRecentTrendComment": "連2跌",
    "URL": "https://tw.stock.yahoo.com/quote/2303/dividend"
  },
  {
    "id": 3045,
    "name": "台灣大",
    "DividendRecentAvg": 0,
    "DividendRecentSlope": null,
    "Category": "通訊網路",
    "CurrentClosingPrice": 102,
    "CurrentTrend": -1.5,
    "CurrentTrendPercent": -0.0145,
    "CurrentTurnover": 9212,
    "CurrentPE": 25.12,
    "CurrentPEAvg": 85.1,
    "CurrentRecentTrendPercent": 0.0145,
    "CurrentRecentTrendComment": "漲→跌",
    "URL": "https://tw.stock.yahoo.com/quote/3045/dividend"
  },
  {
    "id": 2603,
    "name": "長榮",
    "DividendRecentAvg": 0,
    "DividendRecentSlope": null,
    "Category": "航運",
    "CurrentClosingPrice": 172.5,
    "CurrentTrend": 4.5,
    "CurrentTrendPercent": 0.0268,
    "CurrentTurnover": 52298,
    "CurrentPE": 10.33,
    "CurrentPEAvg": 26.05,
    "CurrentRecentTrendPercent": 0.0268,
    "CurrentRecentTrendComment": "跌→漲",
    "URL": "https://tw.stock.yahoo.com/quote/2603/dividend"
  },
  {
    "id": 3533,
    "name": "嘉澤",
    "DividendRecentAvg": 0,
    "DividendRecentSlope": null,
    "Category": "電子零組件",
    "CurrentClosingPrice": 1365,
    "CurrentTrend": -115,
    "CurrentTrendPercent": -0.0777,
    "CurrentTurnover": 1812,
    "CurrentPE": 27.17,
    "CurrentPEAvg": 45.51,
    "CurrentRecentTrendPercent": 0.0777,
    "CurrentRecentTrendComment": "漲→跌",
    "URL": "https://tw.stock.yahoo.com/quote/3533/dividend"
  },
  {
    "id": 9917,
    "name": "中保科",
    "DividendRecentAvg": 0,
    "DividendRecentSlope": null,
    "Category": "其他",
    "CurrentClosingPrice": 126,
    "CurrentTrend": -3.5,
    "CurrentTrendPercent": -0.027,
    "CurrentTurnover": 792,
    "CurrentPE": 21.58,
    "CurrentPEAvg": 22.81,
    "CurrentRecentTrendPercent": 0.027,
    "CurrentRecentTrendComment": "連2漲→跌",
    "URL": "https://tw.stock.yahoo.com/quote/9917/dividend"
  },
  {
    "id": 2308,
    "name": "台達電",
    "DividendRecentAvg": 0,
    "DividendRecentSlope": null,
    "Category": "電子零組件",
    "CurrentClosingPrice": 298.5,
    "CurrentTrend": -10.5,
    "CurrentTrendPercent": -0.034,
    "CurrentTurnover": 13718,
    "CurrentPE": 23.23,
    "CurrentPEAvg": 45.51,
    "CurrentRecentTrendPercent": 0.034,
    "CurrentRecentTrendComment": "連2漲→跌",
    "URL": "https://tw.stock.yahoo.com/quote/2308/dividend"
  },
  {
    "id": 3711,
    "name": "日月光投控",
    "DividendRecentAvg": 0,
    "DividendRecentSlope": null,
    "Category": "半導體",
    "CurrentClosingPrice": 146,
    "CurrentTrend": -5,
    "CurrentTrendPercent": -0.0331,
    "CurrentTurnover": 36183,
    "CurrentPE": 19.84,
    "CurrentPEAvg": 69.96,
    "CurrentRecentTrendPercent": 0.0641,
    "CurrentRecentTrendComment": "連2跌",
    "URL": "https://tw.stock.yahoo.com/quote/3711/dividend"
  },
  {
    "id": 2201,
    "name": "裕隆",
    "DividendRecentAvg": 0,
    "DividendRecentSlope": -999,
    "Category": "",
    "CurrentClosingPrice": 0,
    "CurrentTurnover": 0,
    "CurrentPEAvg": 0,
    "URL": "https://tw.stock.yahoo.com/quote/2201/dividend"
  },
  {
    "id": 2606,
    "name": "裕民",
    "DividendRecentAvg": 0,
    "DividendRecentSlope": null,
    "Category": "航運",
    "CurrentClosingPrice": 55.3,
    "CurrentTrend": 1.6,
    "CurrentTrendPercent": 0.0298,
    "CurrentTurnover": 16619,
    "CurrentPE": 17.07,
    "CurrentPEAvg": 26.05,
    "CurrentRecentTrendPercent": 0.0298,
    "CurrentRecentTrendComment": "平→漲",
    "URL": "https://tw.stock.yahoo.com/quote/2606/dividend"
  },
  {
    "id": 3576,
    "name": "聯合再生",
    "DividendRecentAvg": 0,
    "DividendRecentSlope": 0,
    "Category": "光電",
    "CurrentClosingPrice": 12,
    "CurrentTrend": -0.25,
    "CurrentTrendPercent": -0.0204,
    "CurrentTurnover": 46449,
    "CurrentPE": 0,
    "CurrentPEAvg": 0,
    "CurrentRecentTrendPercent": 0.0204,
    "CurrentRecentTrendComment": "連2漲→跌",
    "URL": "https://tw.stock.yahoo.com/quote/3576/dividend"
  },
  {
    "id": 9921,
    "name": "巨大",
    "DividendRecentAvg": 0,
    "DividendRecentSlope": null,
    "Category": "運動休閒",
    "CurrentClosingPrice": 215.5,
    "CurrentTrend": -9.5,
    "CurrentTrendPercent": -0.0422,
    "CurrentTurnover": 2276,
    "CurrentPE": 24.83,
    "CurrentPEAvg": 26.62,
    "CurrentRecentTrendPercent": 0.0422,
    "CurrentRecentTrendComment": "漲→跌",
    "URL": "https://tw.stock.yahoo.com/quote/9921/dividend"
  },
  {
    "id": 2317,
    "name": "鴻海",
    "DividendRecentAvg": 0,
    "DividendRecentSlope": null,
    "Category": "其他電子",
    "CurrentClosingPrice": 143,
    "CurrentTrend": -5,
    "CurrentTrendPercent": -0.0338,
    "CurrentTurnover": 132464,
    "CurrentPE": 13.95,
    "CurrentPEAvg": 24.08,
    "CurrentRecentTrendPercent": 0.0338,
    "CurrentRecentTrendComment": "連2漲→跌",
    "URL": "https://tw.stock.yahoo.com/quote/2317/dividend"
  },
  {
    "id": 4904,
    "name": "遠傳",
    "DividendRecentAvg": 0,
    "DividendRecentSlope": null,
    "Category": "通訊網路",
    "CurrentClosingPrice": 80.2,
    "CurrentTrend": -0.2,
    "CurrentTrendPercent": -0.0025,
    "CurrentTurnover": 10558,
    "CurrentPE": 25.87,
    "CurrentPEAvg": 85.1,
    "CurrentRecentTrendPercent": 0.0025,
    "CurrentRecentTrendComment": "平→跌",
    "URL": "https://tw.stock.yahoo.com/quote/4904/dividend"
  },
  {
    "id": 2227,
    "name": "裕日車",
    "DividendRecentAvg": 0,
    "DividendRecentSlope": 0,
    "Category": "汽車",
    "CurrentClosingPrice": 122,
    "CurrentTrend": -4.5,
    "CurrentTrendPercent": -0.0356,
    "CurrentTurnover": 120,
    "CurrentPE": 31.52,
    "CurrentPEAvg": 50.73,
    "CurrentRecentTrendPercent": 0.0506,
    "CurrentRecentTrendComment": "連2跌",
    "URL": "https://tw.stock.yahoo.com/quote/2227/dividend"
  },
  {
    "id": 2609,
    "name": "陽明",
    "DividendRecentAvg": 0,
    "DividendRecentSlope": null,
    "Category": "航運",
    "CurrentClosingPrice": 45.15,
    "CurrentTrend": 1.35,
    "CurrentTrendPercent": 0.0308,
    "CurrentTurnover": 59225,
    "CurrentPE": 32.96,
    "CurrentPEAvg": 26.05,
    "CurrentRecentTrendPercent": 0.0308,
    "CurrentRecentTrendComment": "跌→漲",
    "URL": "https://tw.stock.yahoo.com/quote/2609/dividend"
  },
  {
    "id": 4938,
    "name": "和碩",
    "DividendRecentAvg": 0,
    "DividendRecentSlope": null,
    "Category": "電腦週邊",
    "CurrentClosingPrice": 94.8,
    "CurrentTrend": -1.8,
    "CurrentTrendPercent": -0.0186,
    "CurrentTurnover": 16465,
    "CurrentPE": 16.07,
    "CurrentPEAvg": 119.56,
    "CurrentRecentTrendPercent": 0.0186,
    "CurrentRecentTrendComment": "連2漲→跌",
    "URL": "https://tw.stock.yahoo.com/quote/4938/dividend"
  },
  {
    "id": 2610,
    "name": "華航",
    "DividendRecentAvg": 0,
    "DividendRecentSlope": null,
    "Category": "航運",
    "CurrentClosingPrice": 19.45,
    "CurrentTrend": -0.15,
    "CurrentTrendPercent": -0.0077,
    "CurrentTurnover": 42262,
    "CurrentPE": 17.21,
    "CurrentPEAvg": 26.05,
    "CurrentRecentTrendPercent": 0.0077,
    "CurrentRecentTrendComment": "漲→跌",
    "URL": "https://tw.stock.yahoo.com/quote/2610/dividend"
  },
  {
    "id": 3661,
    "name": "世芯-KY",
    "DividendRecentAvg": 0,
    "DividendRecentSlope": null,
    "Category": "半導體",
    "CurrentClosingPrice": 2860,
    "CurrentTrend": -175,
    "CurrentTrendPercent": -0.0577,
    "CurrentTurnover": 3974,
    "CurrentPE": 63.92,
    "CurrentPEAvg": 69.96,
    "CurrentRecentTrendPercent": 0.0577,
    "CurrentRecentTrendComment": "連3漲→跌",
    "URL": "https://tw.stock.yahoo.com/quote/3661/dividend"
  },
  {
    "id": 2313,
    "name": "華通",
    "DividendRecentAvg": 0,
    "DividendRecentSlope": 0,
    "Category": "電子零組件",
    "CurrentClosingPrice": 76.1,
    "CurrentTrend": -1.4,
    "CurrentTrendPercent": -0.0181,
    "CurrentTurnover": 20178,
    "CurrentPE": 21.74,
    "CurrentPEAvg": 45.51,
    "CurrentRecentTrendPercent": 0.0244,
    "CurrentRecentTrendComment": "連2跌",
    "URL": "https://tw.stock.yahoo.com/quote/2313/dividend"
  },
  {
    "id": 2357,
    "name": "華碩",
    "DividendRecentAvg": 0,
    "DividendRecentSlope": null,
    "Category": "電腦週邊",
    "CurrentClosingPrice": 413.5,
    "CurrentTrend": -13.5,
    "CurrentTrendPercent": -0.0316,
    "CurrentTurnover": 4640,
    "CurrentPE": 19.29,
    "CurrentPEAvg": 119.56,
    "CurrentRecentTrendPercent": 0.035,
    "CurrentRecentTrendComment": "連2跌",
    "URL": "https://tw.stock.yahoo.com/quote/2357/dividend"
  },
  {
    "id": 5876,
    "name": "上海商銀",
    "DividendRecentAvg": 0,
    "DividendRecentSlope": null,
    "Category": "金融業",
    "CurrentClosingPrice": 45,
    "CurrentTrend": -1.05,
    "CurrentTrendPercent": -0.0228,
    "CurrentTurnover": 12473,
    "CurrentPE": 14.9,
    "CurrentPEAvg": 14.1,
    "CurrentRecentTrendPercent": 0.0302,
    "CurrentRecentTrendComment": "連2跌",
    "URL": "https://tw.stock.yahoo.com/quote/5876/dividend"
  },
  {
    "id": 2324,
    "name": "仁寶",
    "DividendRecentAvg": 0,
    "DividendRecentSlope": 0,
    "Category": "電腦週邊",
    "CurrentClosingPrice": 35.3,
    "CurrentTrend": -0.75,
    "CurrentTrendPercent": -0.0208,
    "CurrentTurnover": 28442,
    "CurrentPE": 20.06,
    "CurrentPEAvg": 119.56,
    "CurrentRecentTrendPercent": 0.0208,
    "CurrentRecentTrendComment": "連2漲→跌",
    "URL": "https://tw.stock.yahoo.com/quote/2324/dividend"
  },
  {
    "id": 3682,
    "name": "亞太電",
    "DividendRecentAvg": 0,
    "DividendRecentSlope": -999,
    "Category": "",
    "CurrentClosingPrice": 0,
    "CurrentTurnover": 0,
    "CurrentPEAvg": 0,
    "URL": "https://tw.stock.yahoo.com/quote/3682/dividend"
  },
  {
    "id": 2379,
    "name": "瑞昱",
    "DividendRecentAvg": 0,
    "DividendRecentSlope": null,
    "Category": "半導體",
    "CurrentClosingPrice": 552,
    "CurrentTrend": -22,
    "CurrentTrendPercent": -0.0383,
    "CurrentTurnover": 5145,
    "CurrentPE": 30.92,
    "CurrentPEAvg": 69.96,
    "CurrentRecentTrendPercent": 0.0383,
    "CurrentRecentTrendComment": "連2漲→跌",
    "URL": "https://tw.stock.yahoo.com/quote/2379/dividend"
  },
  {
    "id": 5880,
    "name": "合庫金",
    "DividendRecentAvg": 0,
    "DividendRecentSlope": -999,
    "Category": "",
    "CurrentClosingPrice": 0,
    "CurrentTurnover": 0,
    "CurrentPEAvg": 0,
    "URL": "https://tw.stock.yahoo.com/quote/5880/dividend"
  },
  {
    "id": 2337,
    "name": "旺宏",
    "DividendRecentAvg": 0,
    "DividendRecentSlope": null,
    "Category": "半導體",
    "CurrentClosingPrice": 25.95,
    "CurrentTrend": -0.3,
    "CurrentTrendPercent": -0.0114,
    "CurrentTurnover": 18279,
    "CurrentPE": 0,
    "CurrentPEAvg": 0,
    "CurrentRecentTrendPercent": 0.017,
    "CurrentRecentTrendComment": "連2跌",
    "URL": "https://tw.stock.yahoo.com/quote/2337/dividend"
  },
  {
    "id": 2809,
    "name": "京城銀",
    "DividendRecentAvg": 0,
    "DividendRecentSlope": null,
    "Category": "金融業",
    "CurrentClosingPrice": 54,
    "CurrentTrend": -2.9,
    "CurrentTrendPercent": -0.051,
    "CurrentTurnover": 14448,
    "CurrentPE": 9.66,
    "CurrentPEAvg": 14.1,
    "CurrentRecentTrendPercent": 0.051,
    "CurrentRecentTrendComment": "連2漲→跌",
    "URL": "https://tw.stock.yahoo.com/quote/2809/dividend"
  },
  {
    "id": 3702,
    "name": "大聯大",
    "DividendRecentAvg": 0,
    "DividendRecentSlope": null,
    "Category": "電子通路",
    "CurrentClosingPrice": 88.7,
    "CurrentTrend": -0.6,
    "CurrentTrendPercent": -0.0067,
    "CurrentTurnover": 14731,
    "CurrentPE": 20.53,
    "CurrentPEAvg": 79.2,
    "CurrentRecentTrendPercent": 0.04,
    "CurrentRecentTrendComment": "連2跌",
    "URL": "https://tw.stock.yahoo.com/quote/3702/dividend"
  },
  {
    "id": 6415,
    "name": "矽力-KY",
    "DividendRecentAvg": 0,
    "DividendRecentSlope": 0,
    "Category": "半導體",
    "CurrentClosingPrice": 336,
    "CurrentTrend": -37,
    "CurrentTrendPercent": -0.0992,
    "CurrentTurnover": 4771,
    "CurrentPE": 173.2,
    "CurrentPEAvg": 69.96,
    "CurrentRecentTrendPercent": 0.0992,
    "CurrentRecentTrendComment": "漲→跌",
    "URL": "https://tw.stock.yahoo.com/quote/6415/dividend"
  },
  {
    "id": 6505,
    "name": "台塑化",
    "DividendRecentAvg": 0,
    "DividendRecentSlope": null,
    "Category": "油電燃氣",
    "CurrentClosingPrice": 69.3,
    "CurrentTrend": -1,
    "CurrentTrendPercent": -0.0142,
    "CurrentTurnover": 7509,
    "CurrentPE": 30.13,
    "CurrentPEAvg": 27.51,
    "CurrentRecentTrendPercent": 0.0142,
    "CurrentRecentTrendComment": "平→跌",
    "URL": "https://tw.stock.yahoo.com/quote/6505/dividend"
  },
  {
    "id": 2345,
    "name": "智邦",
    "DividendRecentAvg": 0,
    "DividendRecentSlope": null,
    "Category": "通訊網路",
    "CurrentClosingPrice": 401,
    "CurrentTrend": -8,
    "CurrentTrendPercent": -0.0196,
    "CurrentTurnover": 4521,
    "CurrentPE": 25.09,
    "CurrentPEAvg": 85.1,
    "CurrentRecentTrendPercent": 0.0196,
    "CurrentRecentTrendComment": "漲→跌",
    "URL": "https://tw.stock.yahoo.com/quote/2345/dividend"
  },
  {
    "id": 2823,
    "name": "中壽",
    "DividendRecentAvg": 0,
    "DividendRecentSlope": -999,
    "Category": "",
    "CurrentClosingPrice": 0,
    "CurrentTurnover": 0,
    "CurrentPEAvg": 0,
    "URL": "https://tw.stock.yahoo.com/quote/2823/dividend"
  },
  {
    "id": 2408,
    "name": "南亞科",
    "DividendRecentAvg": 0,
    "DividendRecentSlope": 0,
    "Category": "半導體",
    "CurrentClosingPrice": 62,
    "CurrentTrend": -2.3,
    "CurrentTrendPercent": -0.0358,
    "CurrentTurnover": 18315,
    "CurrentPE": 0,
    "CurrentPEAvg": 0,
    "CurrentRecentTrendPercent": 0.1365,
    "CurrentRecentTrendComment": "連5跌",
    "URL": "https://tw.stock.yahoo.com/quote/2408/dividend"
  },
  {
    "id": 6669,
    "name": "緯穎",
    "DividendRecentAvg": 0,
    "DividendRecentSlope": -999,
    "Category": "",
    "CurrentClosingPrice": 0,
    "CurrentTurnover": 0,
    "CurrentPEAvg": 0,
    "URL": "https://tw.stock.yahoo.com/quote/6669/dividend"
  },
  {
    "id": 2347,
    "name": "聯強",
    "DividendRecentAvg": 0,
    "DividendRecentSlope": null,
    "Category": "電子通路",
    "CurrentClosingPrice": 77.3,
    "CurrentTrend": 0.4,
    "CurrentTrendPercent": 0.0052,
    "CurrentTurnover": 13151,
    "CurrentPE": 17.69,
    "CurrentPEAvg": 79.2,
    "CurrentRecentTrendPercent": 0.0052,
    "CurrentRecentTrendComment": "跌→漲",
    "URL": "https://tw.stock.yahoo.com/quote/2347/dividend"
  },
  {
    "id": 4958,
    "name": "臻鼎-KY",
    "DividendRecentAvg": 0,
    "DividendRecentSlope": 0,
    "Category": "電子零組件",
    "CurrentClosingPrice": 112,
    "CurrentTrend": -0.5,
    "CurrentTrendPercent": -0.0044,
    "CurrentTurnover": 10718,
    "CurrentPE": 17.1,
    "CurrentPEAvg": 45.51,
    "CurrentRecentTrendPercent": 0.0132,
    "CurrentRecentTrendComment": "連2跌",
    "URL": "https://tw.stock.yahoo.com/quote/4958/dividend"
  },
  {
    "id": 2412,
    "name": "中華電",
    "DividendRecentAvg": 0,
    "DividendRecentSlope": null,
    "Category": "通訊網路",
    "CurrentClosingPrice": 123,
    "CurrentTrend": -1,
    "CurrentTrendPercent": -0.0081,
    "CurrentTurnover": 17816,
    "CurrentPE": 25.84,
    "CurrentPEAvg": 85.1,
    "CurrentRecentTrendPercent": 0.0081,
    "CurrentRecentTrendComment": "漲→跌",
    "URL": "https://tw.stock.yahoo.com/quote/2412/dividend"
  },
  {
    "id": 8046,
    "name": "南電",
    "DividendRecentAvg": 0,
    "DividendRecentSlope": null,
    "Category": "電子零組件",
    "CurrentClosingPrice": 171.5,
    "CurrentTrend": -7.5,
    "CurrentTrendPercent": -0.0419,
    "CurrentTurnover": 6165,
    "CurrentPE": 19.06,
    "CurrentPEAvg": 45.51,
    "CurrentRecentTrendPercent": 0.1695,
    "CurrentRecentTrendComment": "連8跌",
    "URL": "https://tw.stock.yahoo.com/quote/8046/dividend"
  },
  {
    "id": 2352,
    "name": "佳世達",
    "DividendRecentAvg": 0,
    "DividendRecentSlope": null,
    "Category": "電腦週邊",
    "CurrentClosingPrice": 40.5,
    "CurrentTrend": -0.55,
    "CurrentTrendPercent": -0.0134,
    "CurrentTurnover": 16849,
    "CurrentPE": 26.82,
    "CurrentPEAvg": 119.56,
    "CurrentRecentTrendPercent": 0.017,
    "CurrentRecentTrendComment": "連2跌",
    "URL": "https://tw.stock.yahoo.com/quote/2352/dividend"
  },
  {
    "id": 5269,
    "name": "祥碩",
    "DividendRecentAvg": null,
    "DividendRecentSlope": null,
    "Category": "半導體",
    "CurrentClosingPrice": 1920,
    "CurrentTrend": -125,
    "CurrentTrendPercent": -0.0611,
    "CurrentTurnover": 1018,
    "CurrentPE": 59.78,
    "CurrentPEAvg": 69.96,
    "CurrentRecentTrendPercent": 0.1777,
    "CurrentRecentTrendComment": "連6跌",
    "URL": "https://tw.stock.yahoo.com/quote/5269/dividend"
  },
  {
    "id": 2353,
    "name": "宏碁",
    "DividendRecentAvg": 0,
    "DividendRecentSlope": -999,
    "Category": "",
    "CurrentClosingPrice": 0,
    "CurrentTurnover": 0,
    "CurrentPEAvg": 0,
    "URL": "https://tw.stock.yahoo.com/quote/2353/dividend"
  },
  {
    "id": 2883,
    "name": "開發金",
    "DividendRecentAvg": 0,
    "DividendRecentSlope": 0,
    "Category": "金融業",
    "CurrentClosingPrice": 13.2,
    "CurrentTrend": -0.3,
    "CurrentTrendPercent": -0.0222,
    "CurrentTurnover": 58463,
    "CurrentPE": 12.82,
    "CurrentPEAvg": 14.1,
    "CurrentRecentTrendPercent": 0.0222,
    "CurrentRecentTrendComment": "連2漲→跌",
    "URL": "https://tw.stock.yahoo.com/quote/2883/dividend"
  },
  {
    "id": 2354,
    "name": "鴻準",
    "DividendRecentAvg": 0,
    "DividendRecentSlope": null,
    "Category": "其他電子",
    "CurrentClosingPrice": 55.8,
    "CurrentTrend": -0.7,
    "CurrentTrendPercent": -0.0124,
    "CurrentTurnover": 11353,
    "CurrentPE": 0,
    "CurrentPEAvg": 0,
    "CurrentRecentTrendPercent": 0,
    "CurrentRecentTrendComment": "0",
    "URL": "https://tw.stock.yahoo.com/quote/2354/dividend"
  },
  {
    "id": 2888,
    "name": "新光金",
    "DividendRecentAvg": 0,
    "DividendRecentSlope": 0,
    "Category": "金融業",
    "CurrentClosingPrice": 8.07,
    "CurrentTrend": -0.15,
    "CurrentTrendPercent": -0.0182,
    "CurrentTurnover": 53995,
    "CurrentPE": 0,
    "CurrentPEAvg": 0,
    "CurrentRecentTrendPercent": 0.0182,
    "CurrentRecentTrendComment": "連2漲→跌",
    "URL": "https://tw.stock.yahoo.com/quote/2888/dividend"
  },
  {
    "id": 6176,
    "name": "瑞儀",
    "DividendRecentAvg": 0,
    "DividendRecentSlope": null,
    "Category": "光電",
    "CurrentClosingPrice": 177,
    "CurrentTrend": -5,
    "CurrentTrendPercent": -0.0275,
    "CurrentTurnover": 5740,
    "CurrentPE": 15.59,
    "CurrentPEAvg": 38.75,
    "CurrentRecentTrendPercent": 0.0275,
    "CurrentRecentTrendComment": "連2漲→跌",
    "URL": "https://tw.stock.yahoo.com/quote/6176/dividend"
  },
  {
    "id": 2633,
    "name": "台灣高鐵",
    "DividendRecentAvg": 0,
    "DividendRecentSlope": null,
    "Category": "航運",
    "CurrentClosingPrice": 29.3,
    "CurrentTrend": -0.3,
    "CurrentTrendPercent": -0.0101,
    "CurrentTurnover": 7789,
    "CurrentPE": 21.08,
    "CurrentPEAvg": 26.05,
    "CurrentRecentTrendPercent": 0.0101,
    "CurrentRecentTrendComment": "平→跌",
    "URL": "https://tw.stock.yahoo.com/quote/2633/dividend"
  },
  {
    "id": 1227,
    "name": "佳格",
    "DividendRecentAvg": 0,
    "DividendRecentSlope": null,
    "Category": "食品",
    "CurrentClosingPrice": 37.3,
    "CurrentTrend": -0.25,
    "CurrentTrendPercent": -0.0067,
    "CurrentTurnover": 939,
    "CurrentPE": 27.63,
    "CurrentPEAvg": 43.4,
    "CurrentRecentTrendPercent": 0.0374,
    "CurrentRecentTrendComment": "連7跌",
    "URL": "https://tw.stock.yahoo.com/quote/1227/dividend"
  },
  {
    "id": 2356,
    "name": "英業達",
    "DividendRecentAvg": 0,
    "DividendRecentSlope": null,
    "Category": "電腦週邊",
    "CurrentClosingPrice": 53,
    "CurrentTrend": -0.7,
    "CurrentTrendPercent": -0.013,
    "CurrentTurnover": 44812,
    "CurrentPE": 30.99,
    "CurrentPEAvg": 119.56,
    "CurrentRecentTrendPercent": 0.0203,
    "CurrentRecentTrendComment": "連2跌",
    "URL": "https://tw.stock.yahoo.com/quote/2356/dividend"
  },
  {
    "id": 6213,
    "name": "聯茂",
    "DividendRecentAvg": 0,
    "DividendRecentSlope": null,
    "Category": "電子零組件",
    "CurrentClosingPrice": 110,
    "CurrentTrend": -1.5,
    "CurrentTrendPercent": -0.0135,
    "CurrentTurnover": 12791,
    "CurrentPE": 59.14,
    "CurrentPEAvg": 45.51,
    "CurrentRecentTrendPercent": 0.0135,
    "CurrentRecentTrendComment": "連2漲→跌",
    "URL": "https://tw.stock.yahoo.com/quote/6213/dividend"
  },
  {
    "id": 2360,
    "name": "致茂",
    "DividendRecentAvg": 0,
    "DividendRecentSlope": null,
    "Category": "其他電子",
    "CurrentClosingPrice": 243,
    "CurrentTrend": -8.5,
    "CurrentTrendPercent": -0.0338,
    "CurrentTurnover": 2014,
    "CurrentPE": 25.88,
    "CurrentPEAvg": 24.08,
    "CurrentRecentTrendPercent": 0.0338,
    "CurrentRecentTrendComment": "連2漲→跌",
    "URL": "https://tw.stock.yahoo.com/quote/2360/dividend"
  },
  {
    "id": 6239,
    "name": "力成",
    "DividendRecentAvg": 0,
    "DividendRecentSlope": null,
    "Category": "半導體",
    "CurrentClosingPrice": 174,
    "CurrentTrend": -5.5,
    "CurrentTrendPercent": -0.0306,
    "CurrentTurnover": 8019,
    "CurrentPE": 16.23,
    "CurrentPEAvg": 69.96,
    "CurrentRecentTrendPercent": 0.044,
    "CurrentRecentTrendComment": "連2跌",
    "URL": "https://tw.stock.yahoo.com/quote/6239/dividend"
  }
]